Workbook

Sheet Cover
C11: Compact 3-Statement Model
C14: Table of Contents | G14: Model Check
C16: Model | F16: Balance Sheet Balanced? | G16: =IF(SUM(Model!R32:U32)=0,1,0) -> 1

Sheet Model
B2: Income Statement | I2: Cash Flow Statement | O2: Balance Sheet
B4: All figures in USD thousands | E4: 2023 | F4: =E4+1 -> 2024 | G4: =F4+1 -> 2025 | I4: All figures in USD thousands | K4: =E$4 -> 2023 | L4: =F$4 -> 2024 | M4: =G$4 -> 2025 | O4: All figures in USD thousands | R4: =S4-1 -> 2022 | S4: =E$4 -> 2023 | T4: =F$4 -> 2024 | U4: =G$4 -> 2025
I6: CASH FROM OPERATIONS | O6: ASSETS
B7: Revenue | E7: 58000 | F7: 62000 | G7: 65000 | I7: Net Income | J7: ='Model-R'!L40 -> 1 | K7: =E30 -> 7000 | L7: =F30 -> 9000 | M7: =G30 -> 10000 | O7: Cash | Q7: ='Model-R'!L74 -> 1 | R7: 5000 | S7: =K32 -> 11000 | T7: =L32 -> 17000 | U7: =M32 -> 25000
B8: COGS | E8: -30000 | F8: -31000 | G8: -32000 | I8: Depreciation | J8: ='Model-R'!L41 -> 1 | K8: =-E17 -> 4000 | L8: =-F17 -> 4000 | M8: =-G17 -> 4000 | O8: Accounts Receivable | Q8: ='Model-R'!L75 -> 1 | R8: 6000 | S8: =R8-K10 -> 5000 | T8: =S8-L10 -> 4000 | U8: =T8-M10 -> 3000
B9: Gross Profit | D9: ='Model-R'!L10 -> 1 | E9: =SUM(E7:E8) -> 28000 | F9: =SUM(F7:F8) -> 31000 | G9: =SUM(G7:G8) -> 33000 | I9: Deferred Tax | J9: ='Model-R'!L42 -> 1 | K9: =-E26 -> 2000 | L9: =-F26 -> 2000 | M9: =-G26 -> 2000 | O9: Inventory | Q9: ='Model-R'!L76 -> 1 | R9: 2000 | S9: =R9-K11 -> 3000 | T9: =S9-L11 -> 4000 | U9: =T9-M11 -> 5000
I10: Cash from Accounts Receivable | K10: 1000 | L10: 1000 | M10: 1000 | O10: Property Plant & Equipment | Q10: ='Model-R'!L77 -> 1 | R10: 65000 | S10: =R10-K17-K8 -> 65000 | T10: =S10-L17-L8 -> 65000 | U10: =T10-M17-M8 -> 65000
I11: Cash from Inventory | K11: -1000 | L11: -1000 | M11: -1000 | O11: Total Assets | Q11: ='Model-R'!L78 -> 1 | R11: =SUM(R7:R10) -> 78000 | S11: =SUM(S7:S10) -> 84000 | T11: =SUM(T7:T10) -> 90000 | U11: =SUM(U7:U10) -> 98000
B12: SG&A | E12: -6000 | F12: -7000 | G12: -8000 | I12: Cash from Accounts Payable | K12: 1000 | L12: 1000 | M12: 1000
B13: Other | E13: -2000 | F13: -2000 | G13: -2000 | I13: Subtotal | J13: ='Model-R'!L46 -> 1 | K13: =SUM(K7:K12) -> 14000 | L13: =SUM(L7:L12) -> 16000 | M13: =SUM(M7:M12) -> 17000
B14: EBITDA | D14: ='Model-R'!L15 -> 1 | E14: =SUM(E9:E13) -> 20000 | F14: =SUM(F9:F13) -> 22000 | G14: =SUM(G9:G13) -> 23000
O15: LIABILITIES
I16: CASH FROM INVESTING | O16: Accounts Payable | Q16: ='Model-R'!L83 -> 1 | R16: 3000 | S16: =R16+K12 -> 4000 | T16: =S16+L12 -> 5000 | U16: =T16+M12 -> 6000
B17: Depreciation | E17: -4000 | F17: -4000 | G17: -4000 | I17: Capital Expenditure | K17: -4000 | L17: -4000 | M17: -4000 | O17: Line of Credit | Q17: ='Model-R'!L84 -> 1 | R17: 5000 | S17: =R17+K22 -> 4000 | T17: =S17+L22 -> 2000 | U17: =T17+M22 -> 1000
B18: EBIT | D18: ='Model-R'!L19 -> 1 | E18: =SUM(E14:E17) -> 16000 | F18: =SUM(F14:F17) -> 18000 | G18: =SUM(G14:G17) -> 19000 | I18: Subtotal | J18: ='Model-R'!L51 -> 1 | K18: =SUM(K17) -> -4000 | L18: =SUM(L17) -> -4000 | M18: =SUM(M17) -> -4000 | O18: Term Loan | Q18: ='Model-R'!L85 -> 1 | R18: 20000 | S18: =R18+K23 -> 17000 | T18: =S18+L23 -> 14000 | U18: =T18+M23 -> 11000
O19: Deferred Taxes | Q19: ='Model-R'!L86 -> 1 | R19: 1000 | S19: =R19+K9 -> 3000 | T19: =S19+L9 -> 5000 | U19: =T19+M9 -> 7000
O20: Total Liabilities | Q20: ='Model-R'!L87 -> 1 | R20: =SUM(R16:R19) -> 29000 | S20: =SUM(S16:S19) -> 28000 | T20: =SUM(T16:T19) -> 26000 | U20: =SUM(U16:U19) -> 25000
B21: Interest Expense | E21: -6000 | F21: -6000 | G21: -6000 | I21: CASH FROM FINANCING
B22: EBT | D22: ='Model-R'!L23 -> 1 | E22: =SUM(E18:E21) -> 10000 | F22: =SUM(F18:F21) -> 12000 | G22: =SUM(G18:G21) -> 13000 | I22: Line of Credit Issue / (Repay) | K22: -1000 | L22: -2000 | M22: -1000
I23: Term Loan Issue / (Repay) | K23: -3000 | L23: -3000 | M23: -3000
I24: Equity Issue / (Buyback) | K24: 1000 | L24: 0 | M24: 0 | O24: EQUITY
B25: Current Tax | E25: -1000 | F25: -1000 | G25: -1000 | I25: Payment of Dividends | K25: -1000 | L25: -1000 | M25: -1000 | O25: Equity Capital | Q25: ='Model-R'!L92 -> 1 | R25: 44000 | S25: =R25+K24 -> 45000 | T25: =S25+L24 -> 45000 | U25: =T25+M24 -> 45000
B26: Deferred Tax | E26: -2000 | F26: -2000 | G26: -2000 | I26: Subtotal | J26: ='Model-R'!L59 -> 1 | K26: =SUM(K22:K25) -> -4000 | L26: =SUM(L22:L25) -> -6000 | M26: =SUM(M22:M25) -> -5000 | O26: Retained Earnings | Q26: ='Model-R'!L93 -> 1 | R26: 5000 | S26: =R26+K7+K25 -> 11000 | T26: =S26+L7+L25 -> 19000 | U26: =T26+M7+M25 -> 28000
B27: Total Tax | D27: ='Model-R'!L28 -> 1 | E27: =SUM(E25:E26) -> -3000 | F27: =SUM(F25:F26) -> -3000 | G27: =SUM(G25:G26) -> -3000 | O27: Shareholders' Equity | Q27: ='Model-R'!L94 -> 1 | R27: =SUM(R25:R26) -> 49000 | S27: =SUM(S25:S26) -> 56000 | T27: =SUM(T25:T26) -> 64000 | U27: =SUM(U25:U26) -> 73000
I29: CASH BALANCE | O29: Total Liabilities & Equity | Q29: ='Model-R'!L96 -> 1 | R29: =SUM(R20,R27) -> 78000 | S29: =SUM(S20,S27) -> 84000 | T29: =SUM(T20,T27) -> 90000 | U29: =SUM(U20,U27) -> 98000
B30: Net Income | D30: ='Model-R'!L31 -> 1 | E30: =SUM(E22,E27) -> 7000 | F30: =SUM(F22,F27) -> 9000 | G30: =SUM(G22,G27) -> 10000 | I30: Beginning | J30: ='Model-R'!L63 -> 1 | K30: =R7 -> 5000 | L30: =S7 -> 11000 | M30: =T7 -> 17000
I31: Change in Cash | J31: ='Model-R'!L64 -> 1 | K31: =K13+K18+K26 -> 6000 | L31: =L13+L18+L26 -> 6000 | M31: =M13+M18+M26 -> 8000
I32: Ending | J32: ='Model-R'!L65 -> 1 | K32: =SUM(K30:K31) -> 11000 | L32: =SUM(L30:L31) -> 17000 | M32: =SUM(M30:M31) -> 25000 | O32: Check | Q32: ='Model-R'!L99 -> 1 | R32: =R11-R29 -> 0 | S32: =S11-S29 -> 0 | T32: =T11-T29 -> 0 | U32: =U11-U29 -> 0

Sheet Model-R
B3: Income Statement
B5: All figures in USD thousands | F5: 2023 | G5: =F5+1 -> 2024 | H5: =G5+1 -> 2025 | J5: Learner | K5: Correct | L5: Compare
B8: Revenue | F8: 58000 | G8: 62000 | H8: 65000
B9: COGS | F9: -30000 | G9: -31000 | H9: -32000
B10: Gross Profit | F10: =SUM(Model!E7:E8) -> 28000 | G10: =SUM(Model!F7:F8) -> 31000 | H10: =SUM(Model!G7:G8) -> 33000 | J10: =SUM(Model!E9:G9) -> 92000 | K10: =SUM(F10:H10) -> 92000 | L10: {=IF(SUM(ISBLANK(Model!E9:G9)*1)>0,0,IF(J10=K10,1,0))} -> 1
B13: SG&A | F13: -6000 | G13: -7000 | H13: -8000
B14: Other | F14: -2000 | G14: -2000 | H14: -2000
B15: EBITDA | F15: =Model!E9+SUM(Model!E12:E13) -> 20000 | G15: =Model!F9+SUM(Model!F12:F13) -> 22000 | H15: =Model!G9+SUM(Model!G12:G13) -> 23000 | J15: =SUM(Model!E14:G14) -> 65000 | K15: =SUM(F15:H15) -> 65000 | L15: {=IF(SUM(ISBLANK(Model!E14:G14)*1)>0,0,IF(J15=K15,1,0))} -> 1
B18: Depreciation | F18: -4000 | G18: -4000 | H18: -4000
B19: EBIT | F19: =Model!E17+Model!E14 -> 16000 | G19: =Model!F17+Model!F14 -> 18000 | H19: =Model!G17+Model!G14 -> 19000 | J19: =SUM(Model!E18:G18) -> 53000 | K19: =SUM(F19:H19) -> 53000 | L19: {=IF(SUM(ISBLANK(Model!E18:G18)*1)>0,0,IF(J19=K19,1,0))} -> 1
B22: Interest Expense | F22: -6000 | G22: -6000 | H22: -6000
B23: EBT | F23: =Model!E21+Model!E18 -> 10000 | G23: =Model!F21+Model!F18 -> 12000 | H23: =Model!G21+Model!G18 -> 13000 | J23: =SUM(Model!E22:G22) -> 35000 | K23: =SUM(F23:H23) -> 35000 | L23: {=IF(SUM(ISBLANK(Model!E22:G22)*1)>0,0,IF(J23=K23,1,0))} -> 1
B26: Current Tax | F26: -1000 | G26: -1000 | H26: -1000
B27: Deferred Tax | F27: -2000 | G27: -2000 | H27: -2000
B28: Total Tax | F28: =SUM(Model!E25:E26) -> -3000 | G28: =SUM(Model!F25:F26) -> -3000 | H28: =SUM(Model!G25:G26) -> -3000 | J28: =SUM(Model!E27:G27) -> -9000 | K28: =SUM(F28:H28) -> -9000 | L28: {=IF(SUM(ISBLANK(Model!E27:G27)*1)>0,0,IF(J28=K28,1,0))} -> 1
B31: Net Income | F31: =Model!E27+Model!E22 -> 7000 | G31: =Model!F27+Model!F22 -> 9000 | H31: =Model!G27+Model!G22 -> 10000 | J31: =SUM(Model!E30:G30) -> 26000 | K31: =SUM(F31:H31) -> 26000 | L31: {=IF(SUM(ISBLANK(Model!E30:G30)*1)>0,0,IF(J31=K31,1,0))} -> 1
B35: Cash Flow Statement
B37: All figures in USD thousands | F37: =F$5 -> 2023 | G37: =G$5 -> 2024 | H37: =H$5 -> 2025 | J37: Learner | K37: Correct | L37: Compare
B39: CASH FROM OPERATIONS
B40: Net Income | F40: =Model!E30 -> 7000 | G40: =Model!F30 -> 9000 | H40: =Model!G30 -> 10000 | J40: =SUM(Model!K7:M7) -> 26000 | K40: =SUM(F40:H40) -> 26000 | L40: {=IF(SUM(ISBLANK(Model!K7:M7)*1)>0,0,IF(J40=K40,1,0))} -> 1
B41: Depreciation | F41: =-Model!E17 -> 4000 | G41: =-Model!F17 -> 4000 | H41: =-Model!G17 -> 4000 | J41: =SUM(Model!K8:M8) -> 12000 | K41: =SUM(F41:H41) -> 12000 | L41: {=IF(SUM(ISBLANK(Model!K8:M8)*1)>0,0,IF(J41=K41,1,0))} -> 1
B42: Deferred Tax | F42: =-Model!E26 -> 2000 | G42: =-Model!F26 -> 2000 | H42: =-Model!G26 -> 2000 | J42: =SUM(Model!K9:M9) -> 6000 | K42: =SUM(F42:H42) -> 6000 | L42: {=IF(SUM(ISBLANK(Model!K9:M9)*1)>0,0,IF(J42=K42,1,0))} -> 1
B43: Cash from Accounts Receivable | F43: 1000 | G43: 1000 | H43: 1000
B44: Cash from Inventory | F44: -1000 | G44: -1000 | H44: -1000
B45: Cash from Accounts Payable | F45: 1000 | G45: 1000 | H45: 1000
B46: Subtotal | F46: =SUM(Model!K7:K12) -> 14000 | G46: =SUM(Model!L7:L12) -> 16000 | H46: =SUM(Model!M7:M12) -> 17000 | J46: =SUM(Model!K13:M13) -> 47000 | K46: =SUM(F46:H46) -> 47000 | L46: {=IF(SUM(ISBLANK(Model!K13:M13)*1)>0,0,IF(J46=K46,1,0))} -> 1
B49: CASH FROM INVESTING
B50: Capital Expenditure | F50: -4000 | G50: -4000 | H50: -4000
B51: Subtotal | F51: =Model!K17 -> -4000 | G51: =Model!L17 -> -4000 | H51: =Model!M17 -> -4000 | J51: =SUM(Model!K18:M18) -> -12000 | K51: =SUM(F51:H51) -> -12000 | L51: {=IF(SUM(ISBLANK(Model!K18:M18)*1)>0,0,IF(J51=K51,1,0))} -> 1
B54: CASH FROM FINANCING
B55: Line of Credit Issue / (Repay) | F55: -1000 | G55: -2000 | H55: -1000
B56: Term Loan Issue / (Repay) | F56: -3000 | G56: -3000 | H56: -3000
B57: Equity Issue / (Buyback) | F57: 1000 | G57: 0 | H57: 0
B58: Payment of Dividends | F58: -1000 | G58: -1000 | H58: -1000
B59: Subtotal | F59: =SUM(Model!K22:K25) -> -4000 | G59: =SUM(Model!L22:L25) -> -6000 | H59: =SUM(Model!M22:M25) -> -5000 | J59: =SUM(Model!K26:M26) -> -15000 | K59: =SUM(F59:H59) -> -15000 | L59: {=IF(SUM(ISBLANK(Model!K26:M26)*1)>0,0,IF(J59=K59,1,0))} -> 1
B62: CASH BALANCE
B63: Beginning | F63: =Model!R7 -> 5000 | G63: =Model!K32 -> 11000 | H63: =Model!L32 -> 17000 | J63: =SUM(Model!K30:M30) -> 33000 | K63: =SUM(F63:H63) -> 33000 | L63: {=IF(SUM(ISBLANK(Model!K30:M30)*1)>0,0,IF(J63=K63,1,0))} -> 1
B64: Change in Cash | F64: =Model!K13+Model!K18+Model!K26 -> 6000 | G64: =Model!L13+Model!L18+Model!L26 -> 6000 | H64: =Model!M13+Model!M18+Model!M26 -> 8000 | J64: =SUM(Model!K31:M31) -> 20000 | K64: =SUM(F64:H64) -> 20000 | L64: {=IF(SUM(ISBLANK(Model!K31:M31)*1)>0,0,IF(J64=K64,1,0))} -> 1
B65: Ending | F65: =SUM(Model!K30:K31) -> 11000 | G65: =SUM(Model!L30:L31) -> 17000 | H65: =SUM(Model!M30:M31) -> 25000 | J65: =SUM(Model!K32:M32) -> 53000 | K65: =SUM(F65:H65) -> 53000 | L65: {=IF(SUM(ISBLANK(Model!K32:M32)*1)>0,0,IF(J65=K65,1,0))} -> 1
B69: Balance Sheet
B71: All figures in USD thousands | E71: =F71-1 -> 2022 | F71: =F$5 -> 2023 | G71: =G$5 -> 2024 | H71: =H$5 -> 2025 | J71: Learner | K71: Correct | L71: Compare
B73: ASSETS
B74: Cash | E74: 5000 | F74: =Model!K32 -> 11000 | G74: =Model!L32 -> 17000 | H74: =Model!M32 -> 25000 | J74: =SUM(Model!S7:U7) -> 53000 | K74: =SUM(F74:H74) -> 53000 | L74: {=IF(SUM(ISBLANK(Model!S7:U7)*1)>0,0,IF(J74=K74,1,0))} -> 1
B75: Accounts Receivable | E75: 6000 | F75: =Model!R8-Model!K10 -> 5000 | G75: =Model!S8-Model!L10 -> 4000 | H75: =Model!T8-Model!M10 -> 3000 | J75: =SUM(Model!S8:U8) -> 12000 | K75: =SUM(F75:H75) -> 12000 | L75: {=IF(SUM(ISBLANK(Model!S8:U8)*1)>0,0,IF(J75=K75,1,0))} -> 1
B76: Inventory | E76: 2000 | F76: =Model!R9-Model!K11 -> 3000 | G76: =Model!S9-Model!L11 -> 4000 | H76: =Model!T9-Model!M11 -> 5000 | J76: =SUM(Model!S9:U9) -> 12000 | K76: =SUM(F76:H76) -> 12000 | L76: {=IF(SUM(ISBLANK(Model!S9:U9)*1)>0,0,IF(J76=K76,1,0))} -> 1
B77: Property Plant & Equipment | E77: 65000 | F77: =Model!R10-Model!K17-Model!K8 -> 65000 | G77: =Model!S10-Model!L17-Model!L8 -> 65000 | H77: =Model!T10-Model!M17-Model!M8 -> 65000 | J77: =SUM(Model!S10:U10) -> 195000 | K77: =SUM(F77:H77) -> 195000 | L77: {=IF(SUM(ISBLANK(Model!S10:U10)*1)>0,0,IF(J77=K77,1,0))} -> 1
B78: Total Assets | E78: =SUM(Model!R7:R10) -> 78000 | F78: =SUM(Model!S7:S10) -> 84000 | G78: =SUM(Model!T7:T10) -> 90000 | H78: =SUM(Model!U7:U10) -> 98000 | J78: =SUM(Model!R11:U11) -> 350000 | K78: =SUM(E78:H78) -> 350000 | L78: {=IF(SUM(ISBLANK(Model!R11:U11)*1)>0,0,IF(J78=K78,1,0))} -> 1
B82: LIABILITIES
B83: Accounts Payable | E83: 3000 | F83: =Model!R16+Model!K12 -> 4000 | G83: =Model!S16+Model!L12 -> 5000 | H83: =Model!T16+Model!M12 -> 6000 | J83: =SUM(Model!S16:U16) -> 15000 | K83: =SUM(F83:H83) -> 15000 | L83: {=IF(SUM(ISBLANK(Model!S16:U16)*1)>0,0,IF(J83=K83,1,0))} -> 1
B84: Line of Credit | E84: 5000 | F84: =Model!R17+Model!K22 -> 4000 | G84: =Model!S17+Model!L22 -> 2000 | H84: =Model!T17+Model!M22 -> 1000 | J84: =SUM(Model!S17:U17) -> 7000 | K84: =SUM(F84:H84) -> 7000 | L84: {=IF(SUM(ISBLANK(Model!S17:U17)*1)>0,0,IF(J84=K84,1,0))} -> 1
B85: Term Loan | E85: 20000 | F85: =Model!R18+Model!K23 -> 17000 | G85: =Model!S18+Model!L23 -> 14000 | H85: =Model!T18+Model!M23 -> 11000 | J85: =SUM(Model!S18:U18) -> 42000 | K85: =SUM(F85:H85) -> 42000 | L85: {=IF(SUM(ISBLANK(Model!S18:U18)*1)>0,0,IF(J85=K85,1,0))} -> 1
B86: Deferred Taxes | E86: 1000 | F86: =Model!R19+Model!K9 -> 3000 | G86: =Model!S19+Model!L9 -> 5000 | H86: =Model!T19+Model!M9 -> 7000 | J86: =SUM(Model!S19:U19) -> 15000 | K86: =SUM(F86:H86) -> 15000 | L86: {=IF(SUM(ISBLANK(Model!S19:U19)*1)>0,0,IF(J86=K86,1,0))} -> 1
B87: Total Liabilities | E87: =SUM(Model!R16:R19) -> 29000 | F87: =SUM(Model!S16:S19) -> 28000 | G87: =SUM(Model!T16:T19) -> 26000 | H87: =SUM(Model!U16:U19) -> 25000 | J87: =SUM(Model!R20:U20) -> 108000 | K87: =SUM(E87:H87) -> 108000 | L87: {=IF(SUM(ISBLANK(Model!R20:U20)*1)>0,0,IF(J87=K87,1,0))} -> 1
B91: EQUITY
B92: Equity Capital | E92: 44000 | F92: =Model!R25+Model!K24 -> 45000 | G92: =Model!S25+Model!L24 -> 45000 | H92: =Model!T25+Model!M24 -> 45000 | J92: =SUM(Model!S25:U25) -> 135000 | K92: =SUM(F92:H92) -> 135000 | L92: {=IF(SUM(ISBLANK(Model!S25:U25)*1)>0,0,IF(J92=K92,1,0))} -> 1
B93: Retained Earnings | E93: 5000 | F93: =Model!R26+Model!K7+Model!K25 -> 11000 | G93: =Model!S26+Model!L7+Model!L25 -> 19000 | H93: =Model!T26+Model!M7+Model!M25 -> 28000 | J93: =SUM(Model!S26:U26) -> 58000 | K93: =SUM(F93:H93) -> 58000 | L93: {=IF(SUM(ISBLANK(Model!S26:U26)*1)>0,0,IF(J93=K93,1,0))} -> 1
B94: Shareholders' Equity | E94: =SUM(Model!R25:R26) -> 49000 | F94: =SUM(Model!S25:S26) -> 56000 | G94: =SUM(Model!T25:T26) -> 64000 | H94: =SUM(Model!U25:U26) -> 73000 | J94: =SUM(Model!R27:U27) -> 242000 | K94: =SUM(E94:H94) -> 242000 | L94: {=IF(SUM(ISBLANK(Model!R27:U27)*1)>0,0,IF(J94=K94,1,0))} -> 1
B96: Total Liabilities & Equity | E96: =Model!R27+Model!R20 -> 78000 | F96: =Model!S27+Model!S20 -> 84000 | G96: =Model!T27+Model!T20 -> 90000 | H96: =Model!U27+Model!U20 -> 98000 | J96: =SUM(Model!R29:U29) -> 350000 | K96: =SUM(E96:H96) -> 350000 | L96: {=IF(SUM(ISBLANK(Model!R29:U29)*1)>0,0,IF(J96=K96,1,0))} -> 1
B99: Check | E99: =Model!R11-Model!R29 -> 0 | F99: =Model!S11-Model!S29 -> 0 | G99: =Model!T11-Model!T29 -> 0 | H99: =Model!U11-Model!U29 -> 0 | J99: =SUM(Model!R32:U32) -> 0 | K99: =SUM(E99:H99) -> 0 | L99: {=IF(SUM(ISBLANK(Model!R32:U32)*1)>0,0,IF(J99=K99,1,0))} -> 1
